fastexception
