Metadata-Version: 2.1
Name: fastexception
Version: 0.1.5.1
Home-page: https://github.com/mojtabapaso/fastexception
Author: Mojtaba
Author-email: mojtabapaso@gamil.com
License: MIT
Keywords: FastAPI Tools Fast Exception
Classifier: Programming Language :: Python :: 3
Classifier: License :: OSI Approved :: MIT License
Classifier: Operating System :: OS Independent
License-File: LICENSE
